fhir_simple/__init__.py
fhir_simple-0.1.0.dist-info/licenses/LICENSE
fhir_simple-0.1.0.dist-info/METADATA
fhir_simple-0.1.0.dist-info/WHEEL
fhir_simple-0.1.0.dist-info/top_level.txt
fhir_simple-0.1.0.dist-info/RECORD
