Metadata-Version: 2.4
Name: fhir_simple
Version: 0.1.0
Summary: A library to simplify FHIR Patient objects to basic JSON.
Author: Bhushan Varade
Author-email: Bhushan Varade <bvarade02@gmail.com>
License: MIT
Keywords: fhir,patient,json,healthcare
Requires-Python: >=3.6
License-File: LICENSE
Dynamic: author
Dynamic: license-file
Dynamic: requires-python
